a2dr/__init__.py
a2dr/acceleration.py
a2dr/precondition.py
a2dr/solver.py
a2dr/utilities.py
a2dr/proximal/__init__.py
a2dr/proximal/composition.py
a2dr/proximal/constraint.py
a2dr/proximal/elementwise.py
a2dr/proximal/interface.py
a2dr/proximal/matrix.py
a2dr/proximal/misc.py
a2dr/proximal/norm.py
a2dr/proximal/projection.py
a2dr/proximal/quadratic.py
a2dr/tests/__init__.py
a2dr/tests/base_test.py
a2dr/tests/test_basic.py
a2dr/tests/test_precondition.py
a2dr/tests/test_projection.py
a2dr/tests/test_proximal.py
a2dr-0.2.3.post2.dist-info/LICENSE
a2dr-0.2.3.post2.dist-info/METADATA
a2dr-0.2.3.post2.dist-info/WHEEL
a2dr-0.2.3.post2.dist-info/top_level.txt
a2dr-0.2.3.post2.dist-info/RECORD
