Metadata-Version: 2.1
Name: a2dr
Version: 0.2.3.post2
Summary: A Python package for type-II Anderson accelerated Douglas-Rachford splitting (A2DR).
Home-page: https://github.com/cvxgrp/a2dr
Author: Anqi Fu, Junzi Zhang, Stephen Boyd
Author-email: contact.a2dr.solver@gmail.com
License: Apache License, Version 2.0
Platform: UNKNOWN
Requires-Dist: matplotlib
Requires-Dist: cvxpy (>=1.0.25)
Requires-Dist: numpy (>=1.16)
Requires-Dist: scipy (>=1.2.1)
